rebrandly_sdk/__init__.py
rebrandly_sdk/domains.py
rebrandly_sdk/links.py
rebrandly_sdk/paginated_response.py
rebrandly_sdk/rebrandly_client.py
rebrandly_sdk/workspaces.py
rebrandly_sdk-0.0.1.dist-info/METADATA
rebrandly_sdk-0.0.1.dist-info/WHEEL
rebrandly_sdk-0.0.1.dist-info/licenses/LICENSE
rebrandly_sdk-0.0.1.dist-info/RECORD
