Metadata-Version: 2.4
Name: rebrandly-sdk
Version: 0.0.1
Summary: A Python SDK to wrap Rebrandly's API
Project-URL: Homepage, https://github.com/rebrandly/rebrandly-python
Author-email: Rebrandly Devs <dev@rebrandly.com>
License-Expression: MIT
License-File: LICENSE
Classifier: Operating System :: OS Independent
Classifier: Programming Language :: Python :: 3
Requires-Python: >=3.8
Requires-Dist: pytest
Requires-Dist: python-dotenv==1.0.1
Requires-Dist: requests~=2.28.2
